Workbook

Sheet Dashboard
A1: SALES & INVENTORY ANALYTICS DASHBOARD
A4: TOTAL REVENUE | D4: GROSS PROFIT | G4: PROFIT MARGIN | J4: ORDERS | M4: UNITS SOLD
A5: =SUMIFS(Sales_Data!$I:$I,Sales_Data!$M:$M,"Completed") | D5: =SUMIFS(Sales_Data!$K:$K,Sales_Data!$M:$M,"Completed") | G5: =IFERROR(B5/D5,0) | J5: =COUNTIF(Sales_Data!$M:$M,"Completed") | M5: =SUMIFS(Sales_Data!$E:$E,Sales_Data!$M:$M,"Completed")
A8: ANALYST WATCHLIST | H8: BUSINESS MIX
A9: Low-stock products | B9: =COUNTIF(Inventory_Analysis!$J:$J,"REORDER")+COUNTIF(Inventory_Analysis!$J:$J,"REORDER NOW") | H9: Channel | I9: Revenue | J9: Share
A10: Critical stock items | B10: =COUNTIF(Products!$O:$O,"CRITICAL") | H10: Website | I10: =SUMIFS(Sales_Data!$I:$I,Sales_Data!$N:$N,H10,Sales_Data!$M:$M,"Completed") | J10: =IFERROR(I10/SUM($I$10:$I$13),0)
A11: Top product by revenue | B11: =INDEX(Products!$B$4:$B$15,MATCH(MAX(Products!$K$4:$K$15),Products!$K$4:$K$15,0)) | H11: Facebook | I11: =SUMIFS(Sales_Data!$I:$I,Sales_Data!$N:$N,H11,Sales_Data!$M:$M,"Completed") | J11: =IFERROR(I11/SUM($I$10:$I$13),0)
A12: Best product margin | B12: =INDEX(Products!$B$4:$B$15,MATCH(MAX(Products!$M$4:$M$15),Products!$M$4:$M$15,0)) | H12: TikTok | I12: =SUMIFS(Sales_Data!$I:$I,Sales_Data!$N:$N,H12,Sales_Data!$M:$M,"Completed") | J12: =IFERROR(I12/SUM($I$10:$I$13),0)
H13: Walk-in | I13: =SUMIFS(Sales_Data!$I:$I,Sales_Data!$N:$N,H13,Sales_Data!$M:$M,"Completed") | J13: =IFERROR(I13/SUM($I$10:$I$13),0)

Sheet Sales_Data
A1: Order_ID | B1: Order_Date | C1: Customer_ID | D1: Product_ID | E1: Quantity | F1: Unit_Price | G1: Unit_Cost | H1: Discount | I1: Sales_Revenue | J1: COGS | K1: Gross_Profit | L1: Payment_Method | M1: Order_Status | N1: Channel
A2: ORD00001 | B2: 46217 | C2: C020 | D2: P002 | E2: 1 | F2: 5495 | G2: 3500 | H2: 0 | I2: 5495 | J2: 3500 | K2: 1995 | L2: Card | M2: Completed | N2: Walk-in
A3: ORD00002 | B3: 46297 | C3: C003 | D3: P002 | E3: 4 | F3: 5495 | G3: 3500 | H3: 0.03 | I3: 21320.6 | J3: 14000 | K3: 7320.6 | L3: Card | M3: Completed | N3: TikTok
A4: ORD00003 | B4: 46121 | C4: C008 | D4: P012 | E4: 1 | F4: 1595 | G4: 900 | H4: 0.1 | I4: 0 | J4: 0 | K4: 0 | L4: Card | M4: Cancelled | N4: Facebook
A5: ORD00004 | B5: 46074 | C5: C027 | D5: P007 | E5: 1 | F5: 5295 | G5: 3300 | H5: 0.1 | I5: 4765.5 | J5: 3300 | K5: 1465.5 | L5: Card | M5: Completed | N5: TikTok
A6: ORD00005 | B6: 46130 | C6: C021 | D6: P011 | E6: 1 | F6: 1495 | G6: 850 | H6: 0.1 | I6: 1345.5 | J6: 850 | K6: 495.5 | L6: GCash | M6: Completed | N6: Facebook
A7: ORD00006 | B7: 46296 | C7: C013 | D7: P012 | E7: 1 | F7: 1595 | G7: 900 | H7: 0.03 | I7: 0 | J7: 0 | K7: 0 | L7: Card | M7: Cancelled | N7: Facebook
A8: ORD00007 | B8: 46189 | C8: C026 | D8: P001 | E8: 1 | F8: 4995 | G8: 3200 | H8: 0 | I8: 4995 | J8: 3200 | K8: 1795 | L8: Card | M8: Completed | N8: Website
A9: ORD00008 | B9: 46131 | C9: C007 | D9: P010 | E9: 3 | F9: 4495 | G9: 2600 | H9: 0 | I9: 13485 | J9: 7800 | K9: 5685 | L9: Maya | M9: Completed | N9: Walk-in
A10: ORD00009 | B10: 46096 | C10: C018 | D10: P005 | E10: 1 | F10: 3695 | G10: 2100 | H10: 0.1 | I10: 3325.5 | J10: 2100 | K10: 1225.5 | L10: Card | M10: Completed | N10: Walk-in
A11: ORD00010 | B11: 46227 | C11: C017 | D11: P006 | E11: 1 | F11: 6295 | G11: 3900 | H11: 0 | I11: 6295 | J11: 3900 | K11: 2395 | L11: Maya | M11: Completed | N11: Website
A12: ORD00011 | B12: 46079 | C12: C014 | D12: P003 | E12: 2 | F12: 5995 | G12: 3800 | H12: 0.1 | I12: 10791 | J12: 7600 | K12: 3191 | L12: GCash | M12: Completed | N12: Walk-in
A13: ORD00012 | B13: 46293 | C13: C022 | D13: P005 | E13: 4 | F13: 3695 | G13: 2100 | H13: 0 | I13: 14780 | J13: 8400 | K13: 6380 | L13: GCash | M13: Completed | N13: TikTok
... A501: ORD00500 | B501: 46174 | C501: C027 | D501: P005 | E501: 1 | F501: 3695 | G501: 2100 | H501: 0 | I501: 3695 | J501: 2100 | K501: 1595 | L501: Cash | M501: Completed | N501: TikTok

Sheet Products
A1: Product_ID | B1: Product_Name | C1: Category | D1: Brand | E1: Unit_Cost | F1: Selling_Price | G1: Current_Stock | I1: PRODUCT PERFORMANCE ANALYSIS
A2: P001 | B2: Nike Air Force 1 | C2: Sneakers | D2: Nike | E2: 3200 | F2: 4995 | G2: 35
A3: P002 | B3: Adidas Samba OG | C3: Sneakers | D3: Adidas | E3: 3500 | F3: 5495 | G3: 28 | I3: Product | J3: Units Sold | K3: Revenue | L3: Gross Profit | M3: Margin % | N3: Stock | O3: Stock Status | P3: Revenue Rank
A4: P003 | B4: New Balance 530 | C4: Sneakers | D4: New Balance | E4: 3800 | F4: 5995 | G4: 22 | I4: =B2 | J4: =SUMIF(Sales_Data!$D:$D,A2,Sales_Data!$E:$E) | K4: =SUMIF(Sales_Data!$D:$D,A2,Sales_Data!$I:$I) | L4: =SUMIF(Sales_Data!$D:$D,A2,Sales_Data!$K:$K) | M4: =IFERROR(L4/K4,0) | N4: =G2 | O4: =IF(N4<=10,"CRITICAL",IF(N4<=20,"LOW","HEALTHY")) | P4: =RANK(K4,$K$4:$K$15,0)
A5: P004 | B5: Vans Old Skool | C5: Sneakers | D5: Vans | E5: 2200 | F5: 3995 | G5: 40 | I5: =B3 | J5: =SUMIF(Sales_Data!$D:$D,A3,Sales_Data!$E:$E) | K5: =SUMIF(Sales_Data!$D:$D,A3,Sales_Data!$I:$I) | L5: =SUMIF(Sales_Data!$D:$D,A3,Sales_Data!$K:$K) | M5: =IFERROR(L5/K5,0) | N5: =G3 | O5: =IF(N5<=10,"CRITICAL",IF(N5<=20,"LOW","HEALTHY")) | P5: =RANK(K5,$K$4:$K$15,0)
A6: P005 | B6: Puma Suede Classic | C6: Sneakers | D6: Puma | E6: 2100 | F6: 3695 | G6: 31 | I6: =B4 | J6: =SUMIF(Sales_Data!$D:$D,A4,Sales_Data!$E:$E) | K6: =SUMIF(Sales_Data!$D:$D,A4,Sales_Data!$I:$I) | L6: =SUMIF(Sales_Data!$D:$D,A4,Sales_Data!$K:$K) | M6: =IFERROR(L6/K6,0) | N6: =G4 | O6: =IF(N6<=10,"CRITICAL",IF(N6<=20,"LOW","HEALTHY")) | P6: =RANK(K6,$K$4:$K$15,0)
A7: P006 | B7: Nike Dunk Low | C7: Sneakers | D7: Nike | E7: 3900 | F7: 6295 | G7: 18 | I7: =B5 | J7: =SUMIF(Sales_Data!$D:$D,A5,Sales_Data!$E:$E) | K7: =SUMIF(Sales_Data!$D:$D,A5,Sales_Data!$I:$I) | L7: =SUMIF(Sales_Data!$D:$D,A5,Sales_Data!$K:$K) | M7: =IFERROR(L7/K7,0) | N7: =G5 | O7: =IF(N7<=10,"CRITICAL",IF(N7<=20,"LOW","HEALTHY")) | P7: =RANK(K7,$K$4:$K$15,0)
A8: P007 | B8: Adidas Campus 00s | C8: Sneakers | D8: Adidas | E8: 3300 | F8: 5295 | G8: 25 | I8: =B6 | J8: =SUMIF(Sales_Data!$D:$D,A6,Sales_Data!$E:$E) | K8: =SUMIF(Sales_Data!$D:$D,A6,Sales_Data!$I:$I) | L8: =SUMIF(Sales_Data!$D:$D,A6,Sales_Data!$K:$K) | M8: =IFERROR(L8/K8,0) | N8: =G6 | O8: =IF(N8<=10,"CRITICAL",IF(N8<=20,"LOW","HEALTHY")) | P8: =RANK(K8,$K$4:$K$15,0)
A9: P008 | B9: Converse Chuck 70 | C9: Sneakers | D9: Converse | E9: 2800 | F9: 4595 | G9: 33 | I9: =B7 | J9: =SUMIF(Sales_Data!$D:$D,A7,Sales_Data!$E:$E) | K9: =SUMIF(Sales_Data!$D:$D,A7,Sales_Data!$I:$I) | L9: =SUMIF(Sales_Data!$D:$D,A7,Sales_Data!$K:$K) | M9: =IFERROR(L9/K9,0) | N9: =G7 | O9: =IF(N9<=10,"CRITICAL",IF(N9<=20,"LOW","HEALTHY")) | P9: =RANK(K9,$K$4:$K$15,0)
A10: P009 | B10: New Balance 550 | C10: Sneakers | D10: New Balance | E10: 3600 | F10: 5795 | G10: 16 | I10: =B8 | J10: =SUMIF(Sales_Data!$D:$D,A8,Sales_Data!$E:$E) | K10: =SUMIF(Sales_Data!$D:$D,A8,Sales_Data!$I:$I) | L10: =SUMIF(Sales_Data!$D:$D,A8,Sales_Data!$K:$K) | M10: =IFERROR(L10/K10,0) | N10: =G8 | O10: =IF(N10<=10,"CRITICAL",IF(N10<=20,"LOW","HEALTHY")) | P10: =RANK(K10,$K$4:$K$15,0)
A11: P010 | B11: Vans Knu Skool | C11: Sneakers | D11: Vans | E11: 2600 | F11: 4495 | G11: 20 | I11: =B9 | J11: =SUMIF(Sales_Data!$D:$D,A9,Sales_Data!$E:$E) | K11: =SUMIF(Sales_Data!$D:$D,A9,Sales_Data!$I:$I) | L11: =SUMIF(Sales_Data!$D:$D,A9,Sales_Data!$K:$K) | M11: =IFERROR(L11/K11,0) | N11: =G9 | O11: =IF(N11<=10,"CRITICAL",IF(N11<=20,"LOW","HEALTHY")) | P11: =RANK(K11,$K$4:$K$15,0)
A12: P011 | B12: Nike Tech Cap | C12: Accessories | D12: Nike | E12: 850 | F12: 1495 | G12: 55 | I12: =B10 | J12: =SUMIF(Sales_Data!$D:$D,A10,Sales_Data!$E:$E) | K12: =SUMIF(Sales_Data!$D:$D,A10,Sales_Data!$I:$I) | L12: =SUMIF(Sales_Data!$D:$D,A10,Sales_Data!$K:$K) | M12: =IFERROR(L12/K12,0) | N12: =G10 | O12: =IF(N12<=10,"CRITICAL",IF(N12<=20,"LOW","HEALTHY")) | P12: =RANK(K12,$K$4:$K$15,0)
A13: P012 | B13: Adidas Waist Bag | C13: Accessories | D13: Adidas | E13: 900 | F13: 1595 | G13: 42 | I13: =B11 | J13: =SUMIF(Sales_Data!$D:$D,A11,Sales_Data!$E:$E) | K13: =SUMIF(Sales_Data!$D:$D,A11,Sales_Data!$I:$I) | L13: =SUMIF(Sales_Data!$D:$D,A11,Sales_Data!$K:$K) | M13: =IFERROR(L13/K13,0) | N13: =G11 | O13: =IF(N13<=10,"CRITICAL",IF(N13<=20,"LOW","HEALTHY")) | P13: =RANK(K13,$K$4:$K$15,0)
I14: =B12 | J14: =SUMIF(Sales_Data!$D:$D,A12,Sales_Data!$E:$E) | K14: =SUMIF(Sales_Data!$D:$D,A12,Sales_Data!$I:$I) | L14: =SUMIF(Sales_Data!$D:$D,A12,Sales_Data!$K:$K) | M14: =IFERROR(L14/K14,0) | N14: =G12 | O14: =IF(N14<=10,"CRITICAL",IF(N14<=20,"LOW","HEALTHY")) | P14: =RANK(K14,$K$4:$K$15,0)
I15: =B13 | J15: =SUMIF(Sales_Data!$D:$D,A13,Sales_Data!$E:$E) | K15: =SUMIF(Sales_Data!$D:$D,A13,Sales_Data!$I:$I) | L15: =SUMIF(Sales_Data!$D:$D,A13,Sales_Data!$K:$K) | M15: =IFERROR(L15/K15,0) | N15: =G13 | O15: =IF(N15<=10,"CRITICAL",IF(N15<=20,"LOW","HEALTHY")) | P15: =RANK(K15,$K$4:$K$15,0)

Sheet Customers
A1: Customer_ID | B1: Customer_Name | C1: City
A2: C001 | B2: Customer 01 | C2: Manila
A3: C002 | B3: Customer 02 | C3: Quezon City
A4: C003 | B4: Customer 03 | C4: Caloocan
A5: C004 | B5: Customer 04 | C5: Makati
A6: C005 | B6: Customer 05 | C6: Makati
A7: C006 | B7: Customer 06 | C7: Pasig
A8: C007 | B8: Customer 07 | C8: Manila
A9: C008 | B9: Customer 08 | C9: Manila
A10: C009 | B10: Customer 09 | C10: Cebu
A11: C010 | B11: Customer 10 | C11: Quezon City
A12: C011 | B12: Customer 11 | C12: Quezon City
... A31: C030 | B31: Customer 30 | C31: Manila

Sheet Monthly_Analysis
A1: Month | B1: Revenue | C1: COGS | D1: Gross Profit | E1: Margin % | F1: Orders | G1: Units Sold | H1: Avg Order Value
A2: 46023 | B2: =SUMIFS(Sales_Data!$I:$I,Sales_Data!$B:$B,">="&A2,Sales_Data!$B:$B,"<"&DATE(YEAR(A2),MONTH(A2)+1,1),Sales_Data!$M:$M,"Completed") | C2: =SUMIFS(Sales_Data!$J:$J,Sales_Data!$B:$B,">="&A2,Sales_Data!$B:$B,"<"&DATE(YEAR(A2),MONTH(A2)+1,1),Sales_Data!$M:$M,"Completed") | D2: =B2-C2 | E2: =IFERROR(D2/B2,0) | F2: =COUNTIFS(Sales_Data!$B:$B,">="&A2,Sales_Data!$B:$B,"<"&DATE(YEAR(A2),MONTH(A2)+1,1),Sales_Data!$M:$M,"Completed") | G2: =SUMIFS(Sales_Data!$E:$E,Sales_Data!$B:$B,">="&A2,Sales_Data!$B:$B,"<"&DATE(YEAR(A2),MONTH(A2)+1,1),Sales_Data!$M:$M,"Completed") | H2: =IFERROR(B2/F2,0)
A3: 46054 | B3: =SUMIFS(Sales_Data!$I:$I,Sales_Data!$B:$B,">="&A3,Sales_Data!$B:$B,"<"&DATE(YEAR(A3),MONTH(A3)+1,1),Sales_Data!$M:$M,"Completed") | C3: =SUMIFS(Sales_Data!$J:$J,Sales_Data!$B:$B,">="&A3,Sales_Data!$B:$B,"<"&DATE(YEAR(A3),MONTH(A3)+1,1),Sales_Data!$M:$M,"Completed") | D3: =B3-C3 | E3: =IFERROR(D3/B3,0) | F3: =COUNTIFS(Sales_Data!$B:$B,">="&A3,Sales_Data!$B:$B,"<"&DATE(YEAR(A3),MONTH(A3)+1,1),Sales_Data!$M:$M,"Completed") | G3: =SUMIFS(Sales_Data!$E:$E,Sales_Data!$B:$B,">="&A3,Sales_Data!$B:$B,"<"&DATE(YEAR(A3),MONTH(A3)+1,1),Sales_Data!$M:$M,"Completed") | H3: =IFERROR(B3/F3,0)
A4: 46082 | B4: =SUMIFS(Sales_Data!$I:$I,Sales_Data!$B:$B,">="&A4,Sales_Data!$B:$B,"<"&DATE(YEAR(A4),MONTH(A4)+1,1),Sales_Data!$M:$M,"Completed") | C4: =SUMIFS(Sales_Data!$J:$J,Sales_Data!$B:$B,">="&A4,Sales_Data!$B:$B,"<"&DATE(YEAR(A4),MONTH(A4)+1,1),Sales_Data!$M:$M,"Completed") | D4: =B4-C4 | E4: =IFERROR(D4/B4,0) | F4: =COUNTIFS(Sales_Data!$B:$B,">="&A4,Sales_Data!$B:$B,"<"&DATE(YEAR(A4),MONTH(A4)+1,1),Sales_Data!$M:$M,"Completed") | G4: =SUMIFS(Sales_Data!$E:$E,Sales_Data!$B:$B,">="&A4,Sales_Data!$B:$B,"<"&DATE(YEAR(A4),MONTH(A4)+1,1),Sales_Data!$M:$M,"Completed") | H4: =IFERROR(B4/F4,0)
A5: 46113 | B5: =SUMIFS(Sales_Data!$I:$I,Sales_Data!$B:$B,">="&A5,Sales_Data!$B:$B,"<"&DATE(YEAR(A5),MONTH(A5)+1,1),Sales_Data!$M:$M,"Completed") | C5: =SUMIFS(Sales_Data!$J:$J,Sales_Data!$B:$B,">="&A5,Sales_Data!$B:$B,"<"&DATE(YEAR(A5),MONTH(A5)+1,1),Sales_Data!$M:$M,"Completed") | D5: =B5-C5 | E5: =IFERROR(D5/B5,0) | F5: =COUNTIFS(Sales_Data!$B:$B,">="&A5,Sales_Data!$B:$B,"<"&DATE(YEAR(A5),MONTH(A5)+1,1),Sales_Data!$M:$M,"Completed") | G5: =SUMIFS(Sales_Data!$E:$E,Sales_Data!$B:$B,">="&A5,Sales_Data!$B:$B,"<"&DATE(YEAR(A5),MONTH(A5)+1,1),Sales_Data!$M:$M,"Completed") | H5: =IFERROR(B5/F5,0)
A6: 46143 | B6: =SUMIFS(Sales_Data!$I:$I,Sales_Data!$B:$B,">="&A6,Sales_Data!$B:$B,"<"&DATE(YEAR(A6),MONTH(A6)+1,1),Sales_Data!$M:$M,"Completed") | C6: =SUMIFS(Sales_Data!$J:$J,Sales_Data!$B:$B,">="&A6,Sales_Data!$B:$B,"<"&DATE(YEAR(A6),MONTH(A6)+1,1),Sales_Data!$M:$M,"Completed") | D6: =B6-C6 | E6: =IFERROR(D6/B6,0) | F6: =COUNTIFS(Sales_Data!$B:$B,">="&A6,Sales_Data!$B:$B,"<"&DATE(YEAR(A6),MONTH(A6)+1,1),Sales_Data!$M:$M,"Completed") | G6: =SUMIFS(Sales_Data!$E:$E,Sales_Data!$B:$B,">="&A6,Sales_Data!$B:$B,"<"&DATE(YEAR(A6),MONTH(A6)+1,1),Sales_Data!$M:$M,"Completed") | H6: =IFERROR(B6/F6,0)
A7: 46174 | B7: =SUMIFS(Sales_Data!$I:$I,Sales_Data!$B:$B,">="&A7,Sales_Data!$B:$B,"<"&DATE(YEAR(A7),MONTH(A7)+1,1),Sales_Data!$M:$M,"Completed") | C7: =SUMIFS(Sales_Data!$J:$J,Sales_Data!$B:$B,">="&A7,Sales_Data!$B:$B,"<"&DATE(YEAR(A7),MONTH(A7)+1,1),Sales_Data!$M:$M,"Completed") | D7: =B7-C7 | E7: =IFERROR(D7/B7,0) | F7: =COUNTIFS(Sales_Data!$B:$B,">="&A7,Sales_Data!$B:$B,"<"&DATE(YEAR(A7),MONTH(A7)+1,1),Sales_Data!$M:$M,"Completed") | G7: =SUMIFS(Sales_Data!$E:$E,Sales_Data!$B:$B,">="&A7,Sales_Data!$B:$B,"<"&DATE(YEAR(A7),MONTH(A7)+1,1),Sales_Data!$M:$M,"Completed") | H7: =IFERROR(B7/F7,0)
A8: 46204 | B8: =SUMIFS(Sales_Data!$I:$I,Sales_Data!$B:$B,">="&A8,Sales_Data!$B:$B,"<"&DATE(YEAR(A8),MONTH(A8)+1,1),Sales_Data!$M:$M,"Completed") | C8: =SUMIFS(Sales_Data!$J:$J,Sales_Data!$B:$B,">="&A8,Sales_Data!$B:$B,"<"&DATE(YEAR(A8),MONTH(A8)+1,1),Sales_Data!$M:$M,"Completed") | D8: =B8-C8 | E8: =IFERROR(D8/B8,0) | F8: =COUNTIFS(Sales_Data!$B:$B,">="&A8,Sales_Data!$B:$B,"<"&DATE(YEAR(A8),MONTH(A8)+1,1),Sales_Data!$M:$M,"Completed") | G8: =SUMIFS(Sales_Data!$E:$E,Sales_Data!$B:$B,">="&A8,Sales_Data!$B:$B,"<"&DATE(YEAR(A8),MONTH(A8)+1,1),Sales_Data!$M:$M,"Completed") | H8: =IFERROR(B8/F8,0)
A9: 46235 | B9: =SUMIFS(Sales_Data!$I:$I,Sales_Data!$B:$B,">="&A9,Sales_Data!$B:$B,"<"&DATE(YEAR(A9),MONTH(A9)+1,1),Sales_Data!$M:$M,"Completed") | C9: =SUMIFS(Sales_Data!$J:$J,Sales_Data!$B:$B,">="&A9,Sales_Data!$B:$B,"<"&DATE(YEAR(A9),MONTH(A9)+1,1),Sales_Data!$M:$M,"Completed") | D9: =B9-C9 | E9: =IFERROR(D9/B9,0) | F9: =COUNTIFS(Sales_Data!$B:$B,">="&A9,Sales_Data!$B:$B,"<"&DATE(YEAR(A9),MONTH(A9)+1,1),Sales_Data!$M:$M,"Completed") | G9: =SUMIFS(Sales_Data!$E:$E,Sales_Data!$B:$B,">="&A9,Sales_Data!$B:$B,"<"&DATE(YEAR(A9),MONTH(A9)+1,1),Sales_Data!$M:$M,"Completed") | H9: =IFERROR(B9/F9,0)
A10: 46266 | B10: =SUMIFS(Sales_Data!$I:$I,Sales_Data!$B:$B,">="&A10,Sales_Data!$B:$B,"<"&DATE(YEAR(A10),MONTH(A10)+1,1),Sales_Data!$M:$M,"Completed") | C10: =SUMIFS(Sales_Data!$J:$J,Sales_Data!$B:$B,">="&A10,Sales_Data!$B:$B,"<"&DATE(YEAR(A10),MONTH(A10)+1,1),Sales_Data!$M:$M,"Completed") | D10: =B10-C10 | E10: =IFERROR(D10/B10,0) | F10: =COUNTIFS(Sales_Data!$B:$B,">="&A10,Sales_Data!$B:$B,"<"&DATE(YEAR(A10),MONTH(A10)+1,1),Sales_Data!$M:$M,"Completed") | G10: =SUMIFS(Sales_Data!$E:$E,Sales_Data!$B:$B,">="&A10,Sales_Data!$B:$B,"<"&DATE(YEAR(A10),MONTH(A10)+1,1),Sales_Data!$M:$M,"Completed") | H10: =IFERROR(B10/F10,0)

Sheet Inventory_Analysis
A1: Product_ID | B1: Product_Name | C1: Category | D1: Current_Stock | E1: Unit_Cost | F1: Stock Value | G1: Units Sold | H1: Avg Monthly Sales | I1: Est. Months Cover | J1: Risk
A2: P001 | B2: Nike Air Force 1 | C2: Sneakers | D2: 35 | E2: 3200 | F2: =D2*E2 | G2: =SUMIF(Sales_Data!$D:$D,A2,Sales_Data!$E:$E) | H2: =G2/9 | I2: =IFERROR(D2/H2,0) | J2: =IF(D2<=10,"REORDER NOW",IF(I2<1,"REORDER","OK"))
A3: P002 | B3: Adidas Samba OG | C3: Sneakers | D3: 28 | E3: 3500 | F3: =D3*E3 | G3: =SUMIF(Sales_Data!$D:$D,A3,Sales_Data!$E:$E) | H3: =G3/9 | I3: =IFERROR(D3/H3,0) | J3: =IF(D3<=10,"REORDER NOW",IF(I3<1,"REORDER","OK"))
A4: P003 | B4: New Balance 530 | C4: Sneakers | D4: 22 | E4: 3800 | F4: =D4*E4 | G4: =SUMIF(Sales_Data!$D:$D,A4,Sales_Data!$E:$E) | H4: =G4/9 | I4: =IFERROR(D4/H4,0) | J4: =IF(D4<=10,"REORDER NOW",IF(I4<1,"REORDER","OK"))
A5: P004 | B5: Vans Old Skool | C5: Sneakers | D5: 40 | E5: 2200 | F5: =D5*E5 | G5: =SUMIF(Sales_Data!$D:$D,A5,Sales_Data!$E:$E) | H5: =G5/9 | I5: =IFERROR(D5/H5,0) | J5: =IF(D5<=10,"REORDER NOW",IF(I5<1,"REORDER","OK"))
A6: P005 | B6: Puma Suede Classic | C6: Sneakers | D6: 31 | E6: 2100 | F6: =D6*E6 | G6: =SUMIF(Sales_Data!$D:$D,A6,Sales_Data!$E:$E) | H6: =G6/9 | I6: =IFERROR(D6/H6,0) | J6: =IF(D6<=10,"REORDER NOW",IF(I6<1,"REORDER","OK"))
A7: P006 | B7: Nike Dunk Low | C7: Sneakers | D7: 18 | E7: 3900 | F7: =D7*E7 | G7: =SUMIF(Sales_Data!$D:$D,A7,Sales_Data!$E:$E) | H7: =G7/9 | I7: =IFERROR(D7/H7,0) | J7: =IF(D7<=10,"REORDER NOW",IF(I7<1,"REORDER","OK"))
A8: P007 | B8: Adidas Campus 00s | C8: Sneakers | D8: 25 | E8: 3300 | F8: =D8*E8 | G8: =SUMIF(Sales_Data!$D:$D,A8,Sales_Data!$E:$E) | H8: =G8/9 | I8: =IFERROR(D8/H8,0) | J8: =IF(D8<=10,"REORDER NOW",IF(I8<1,"REORDER","OK"))
A9: P008 | B9: Converse Chuck 70 | C9: Sneakers | D9: 33 | E9: 2800 | F9: =D9*E9 | G9: =SUMIF(Sales_Data!$D:$D,A9,Sales_Data!$E:$E) | H9: =G9/9 | I9: =IFERROR(D9/H9,0) | J9: =IF(D9<=10,"REORDER NOW",IF(I9<1,"REORDER","OK"))
A10: P009 | B10: New Balance 550 | C10: Sneakers | D10: 16 | E10: 3600 | F10: =D10*E10 | G10: =SUMIF(Sales_Data!$D:$D,A10,Sales_Data!$E:$E) | H10: =G10/9 | I10: =IFERROR(D10/H10,0) | J10: =IF(D10<=10,"REORDER NOW",IF(I10<1,"REORDER","OK"))
A11: P010 | B11: Vans Knu Skool | C11: Sneakers | D11: 20 | E11: 2600 | F11: =D11*E11 | G11: =SUMIF(Sales_Data!$D:$D,A11,Sales_Data!$E:$E) | H11: =G11/9 | I11: =IFERROR(D11/H11,0) | J11: =IF(D11<=10,"REORDER NOW",IF(I11<1,"REORDER","OK"))
A12: P011 | B12: Nike Tech Cap | C12: Accessories | D12: 55 | E12: 850 | F12: =D12*E12 | G12: =SUMIF(Sales_Data!$D:$D,A12,Sales_Data!$E:$E) | H12: =G12/9 | I12: =IFERROR(D12/H12,0) | J12: =IF(D12<=10,"REORDER NOW",IF(I12<1,"REORDER","OK"))
A13: P012 | B13: Adidas Waist Bag | C13: Accessories | D13: 42 | E13: 900 | F13: =D13*E13 | G13: =SUMIF(Sales_Data!$D:$D,A13,Sales_Data!$E:$E) | H13: =G13/9 | I13: =IFERROR(D13/H13,0) | J13: =IF(D13<=10,"REORDER NOW",IF(I13<1,"REORDER","OK"))

Sheet Read_Me
A1: PROFESSIONAL SALES & INVENTORY ANALYTICS WORKBOOK
A2: Purpose | B2: Template for analyzing sales, revenue, profit, products, customers, and inventory.
A3: How to use | B3: Replace the sample rows in Sales_Data, Products, and Customers with your actual database export.
A4: Important | B4: The sample data is fictional and is included only to demonstrate the dashboard.
A5: Recommended workflow | B5: 1) Import clean transaction data → 2) Update product costs/stock → 3) Review Dashboard → 4) Investigate Product/Inventory tabs.
A6: Key analyst questions | B6: What is selling? What is profitable? Which products are declining? Which items are low stock? Who are the best customers?
A7: Data quality | B7: Keep one row per order line in Sales_Data. Use consistent product IDs, dates, quantities, prices, and costs.
